{
  "version": "1.0.0",
  "lastScanned": 1781907183503,
  "projectRoot": "/home/local/SAIL/zhimin/awesome-production-machine-learning",
  "techStack": {
    "languages": [],
    "frameworks": [],
    "packageManager": null,
    "runtime": null
  },
  "build": {
    "buildCommand": null,
    "testCommand": null,
    "lintCommand": null,
    "devCommand": null,
    "scripts": {}
  },
  "conventions": {
    "namingStyle": null,
    "importStyle": null,
    "testPattern": null,
    "fileOrganization": null
  },
  "structure": {
    "isMonorepo": false,
    "workspaces": [],
    "mainDirectories": [],
    "gitBranches": {
      "defaultBranch": "master",
      "branchingStrategy": null
    }
  },
  "customNotes": [],
  "directoryMap": {
    "images": {
      "path": "images",
      "purpose": null,
      "fileCount": 3,
      "lastAccessed": 1781907183498,
      "keyFiles": [
        "list.jpg",
        "mleng.png",
        "video.png"
      ]
    }
  },
  "hotPaths": [],
  "userDirectives": []
}